{
   "uid" : "rs-pontao",
   "evidence" : "http://www.cidadessustentaveis.org.br/signatarios-candidatos",
   "recipient" : {
      "type" : "email",
      "hashed" : false,
      "identity" : "rs-pontao@missing.com"
   },
   "verify" : {
      "url" : "http://badges.nossasaopaulo.org.br/badges/rs-pontao.json",
      "type" : "hosted"
   },
   "nossasaopaulo:partido" : "Partido dos Trabalhadores - PT",
   "badge" : "http://badges.nossasaopaulo.org.br/pcs.json",
   "nossasaopaulo:cidade" : "Pontão",
   "image" : "http://cidadessustentaveis.org.br/sites/default/files/logo.png",
   "issuedOn" : 1466455757,
   "nossasaopaulo:estado" : "RS",
   "nossasaopaulo:prefeito" : "Nelson José Grasselli"
}
